[{"TimeUTC":"2025-11-12 21:22:00","timestampInMs":1762982520120,"requestPath":"tele-fxnfwqv7h-phnxvisioins-projects.vercel.app/favicon.ico","requestMethod":"GET","requestQueryString":"","responseStatusCode":-1,"requestId":"9wbk8-1762982511814-31ab198ded46","requestUserAgent":"Mozilla/5.0 (Macintosh; Intel Mac OS X 10_15_7) AppleWebKit/537.36 (KHTML, like Gecko) Chrome/142.0.0.0 Safari/537.36","level":"fatal","environment":"production","branch":"main","vercelCache":"","type":"lambda","function":"/api/index.py","host":"tele-fxnfwqv7h-phnxvisioins-projects.vercel.app","deploymentDomain":"tele-fxnfwqv7h-phnxvisioins-projects.vercel.app","deploymentId":"dpl_BJL7eZW3Wc3wsRoo1q3xkX92qsn8","durationMs":-1,"region":"iad1","maxMemoryUsed":-1,"memorySize":-1,"message":"Python process exited with exit status: 1. The logs above can help with debugging the issue.","projectId":"prj_Cur5K4TixuWDzJgXyvxVwYeMd2A6","traceId":"","sessionId":"","invocationId":"01K9WZ4H7XE93GKK3W5EDVWE82","instanceId":"","concurrency":-1},{"TimeUTC":"2025-11-12 21:21:58","timestampInMs":1762982518208,"requestPath":"tele-git-main-phnxvisioins-projects.vercel.app/favicon.ico","requestMethod":"GET","requestQueryString":"","responseStatusCode":-1,"requestId":"jxbtc-1762982509695-fe403d4dda17","requestUserAgent":"Mozilla/5.0 (Macintosh; Intel Mac OS X 10_15_7) AppleWebKit/537.36 (KHTML, like Gecko) Chrome/142.0.0.0 Safari/537.36","level":"fatal","environment":"production","branch":"main","vercelCache":"","type":"lambda","function":"/api/index.py","host":"tele-git-main-phnxvisioins-projects.vercel.app","deploymentDomain":"tele-git-main-phnxvisioins-projects.vercel.app","deploymentId":"dpl_BJL7eZW3Wc3wsRoo1q3xkX92qsn8","durationMs":-1,"region":"iad1","maxMemoryUsed":-1,"memorySize":-1,"message":"Python process exited with exit status: 1. The logs above can help with debugging the issue.","projectId":"prj_Cur5K4TixuWDzJgXyvxVwYeMd2A6","traceId":"","sessionId":"","invocationId":"01K9WZ4F6M02Z2B1Y8HPBYMH1C","instanceId":"","concurrency":-1},{"TimeUTC":"2025-11-12 21:21:52","timestampInMs":1762982512227,"requestPath":"tele-fxnfwqv7h-phnxvisioins-projects.vercel.app/favicon.ico","requestMethod":"GET","requestQueryString":"","responseStatusCode":-1,"requestId":"mnlln-1762982494478-d1eeef03c5a0","requestUserAgent":"vercel-favicon/1.0","level":"fatal","environment":"production","branch":"main","vercelCache":"","type":"lambda","function":"/api/index.py","host":"tele-fxnfwqv7h-phnxvisioins-projects.vercel.app","deploymentDomain":"tele-fxnfwqv7h-phnxvisioins-projects.vercel.app","deploymentId":"dpl_BJL7eZW3Wc3wsRoo1q3xkX92qsn8","durationMs":-1,"region":"iad1","maxMemoryUsed":-1,"memorySize":-1,"message":"Python process exited with exit status: 1. The logs above can help with debugging the issue.\nPython process exited with exit status: 1. The logs above can help with debugging the issue.","projectId":"prj_Cur5K4TixuWDzJgXyvxVwYeMd2A6","traceId":"","sessionId":"","invocationId":"01K9WZ409S053T7TB5D9VY3V41","instanceId":"","concurrency":-1},{"TimeUTC":"2025-11-12 21:21:52","timestampInMs":1762982512132,"requestPath":"tele-fxnfwqv7h-phnxvisioins-projects.vercel.app/favicon.ico","requestMethod":"GET","requestQueryString":"","responseStatusCode":-1,"requestId":"sr6cw-1762982503556-247d8e926918","requestUserAgent":"vercel-favicon/1.0","level":"fatal","environment":"production","branch":"main","vercelCache":"","type":"lambda","function":"/api/index.py","host":"tele-fxnfwqv7h-phnxvisioins-projects.vercel.app","deploymentDomain":"tele-fxnfwqv7h-phnxvisioins-projects.vercel.app","deploymentId":"dpl_BJL7eZW3Wc3wsRoo1q3xkX92qsn8","durationMs":-1,"region":"iad1","maxMemoryUsed":-1,"memorySize":-1,"message":"Python process exited with exit status: 1. The logs above can help with debugging the issue.","projectId":"prj_Cur5K4TixuWDzJgXyvxVwYeMd2A6","traceId":"","sessionId":"","invocationId":"01K9WZ495H6A4QGA4RTX3WB2ZW","instanceId":"","concurrency":-1},{"TimeUTC":"2025-11-12 21:21:51","timestampInMs":1762982511869,"requestPath":"tele-fxnfwqv7h-phnxvisioins-projects.vercel.app/favicon.ico","requestMethod":"GET","requestQueryString":"","responseStatusCode":500,"requestId":"9wbk8-1762982511814-31ab198ded46","requestUserAgent":"Mozilla/5.0 (Macintosh; Intel Mac OS X 10_15_7) AppleWebKit/537.36 (KHTML, like Gecko) Chrome/142.0.0.0 Safari/537.36","level":"error","environment":"production","branch":"main","vercelCache":"","type":"lambda","function":"/api/index.py","host":"tele-fxnfwqv7h-phnxvisioins-projects.vercel.app","deploymentDomain":"tele-fxnfwqv7h-phnxvisioins-projects.vercel.app","deploymentId":"dpl_BJL7eZW3Wc3wsRoo1q3xkX92qsn8","durationMs":8222,"region":"iad1","maxMemoryUsed":292,"memorySize":2048,"message":"","projectId":"prj_Cur5K4TixuWDzJgXyvxVwYeMd2A6","traceId":"","sessionId":"","invocationId":"01K9WZ4H7XE93GKK3W5EDVWE82","instanceId":"","concurrency":1},{"TimeUTC":"2025-11-12 21:21:51","timestampInMs":1762982511626,"requestPath":"tele-fxnfwqv7h-phnxvisioins-projects.vercel.app/","requestMethod":"GET","requestQueryString":"","responseStatusCode":-1,"requestId":"m42sb-1762982494181-cd8889e49fb0","requestUserAgent":"Mozilla/5.0 (Macintosh; Intel Mac OS X 10_15_7) AppleWebKit/537.36 (KHTML, like Gecko) Chrome/142.0.0.0 Safari/537.36","level":"fatal","environment":"production","branch":"main","vercelCache":"","type":"lambda","function":"/api/index.py","host":"tele-fxnfwqv7h-phnxvisioins-projects.vercel.app","deploymentDomain":"tele-fxnfwqv7h-phnxvisioins-projects.vercel.app","deploymentId":"dpl_BJL7eZW3Wc3wsRoo1q3xkX92qsn8","durationMs":-1,"region":"iad1","maxMemoryUsed":-1,"memorySize":-1,"message":"Python process exited with exit status: 1. The logs above can help with debugging the issue.\nPython process exited with exit status: 1. The logs above can help with debugging the issue.","projectId":"prj_Cur5K4TixuWDzJgXyvxVwYeMd2A6","traceId":"","sessionId":"","invocationId":"01K9WZ405CTDVP4GFMGJTFZEQD","instanceId":"","concurrency":-1},{"TimeUTC":"2025-11-12 21:21:49","timestampInMs":1762982509780,"requestPath":"tele-git-main-phnxvisioins-projects.vercel.app/favicon.ico","requestMethod":"GET","requestQueryString":"","responseStatusCode":500,"requestId":"jxbtc-1762982509695-fe403d4dda17","requestUserAgent":"Mozilla/5.0 (Macintosh; Intel Mac OS X 10_15_7) AppleWebKit/537.36 (KHTML, like Gecko) Chrome/142.0.0.0 Safari/537.36","level":"error","environment":"production","branch":"main","vercelCache":"","type":"lambda","function":"/api/index.py","host":"tele-git-main-phnxvisioins-projects.vercel.app","deploymentDomain":"tele-git-main-phnxvisioins-projects.vercel.app","deploymentId":"dpl_BJL7eZW3Wc3wsRoo1q3xkX92qsn8","durationMs":8414,"region":"iad1","maxMemoryUsed":292,"memorySize":2048,"message":"","projectId":"prj_Cur5K4TixuWDzJgXyvxVwYeMd2A6","traceId":"","sessionId":"","invocationId":"01K9WZ4F6M02Z2B1Y8HPBYMH1C","instanceId":"","concurrency":1},{"TimeUTC":"2025-11-12 21:21:49","timestampInMs":1762982509650,"requestPath":"tele-fxnfwqv7h-phnxvisioins-projects.vercel.app/","requestMethod":"GET","requestQueryString":"","responseStatusCode":-1,"requestId":"7g5x8-1762982491892-f2e6fa2a9981","requestUserAgent":"vercel-favicon/1.0","level":"fatal","environment":"production","branch":"main","vercelCache":"","type":"lambda","function":"/api/index.py","host":"tele-fxnfwqv7h-phnxvisioins-projects.vercel.app","deploymentDomain":"tele-fxnfwqv7h-phnxvisioins-projects.vercel.app","deploymentId":"dpl_BJL7eZW3Wc3wsRoo1q3xkX92qsn8","durationMs":-1,"region":"iad1","maxMemoryUsed":-1,"memorySize":-1,"message":"Python process exited with exit status: 1. The logs above can help with debugging the issue.\nPython process exited with exit status: 1. The logs above can help with debugging the issue.","projectId":"prj_Cur5K4TixuWDzJgXyvxVwYeMd2A6","traceId":"","sessionId":"","invocationId":"01K9WZ3XRWT7CRNXDXY707X0GP","instanceId":"","concurrency":-1},{"TimeUTC":"2025-11-12 21:21:49","timestampInMs":1762982509564,"requestPath":"tele-git-main-phnxvisioins-projects.vercel.app/","requestMethod":"GET","requestQueryString":"","responseStatusCode":-1,"requestId":"54bv2-1762982491665-4d8c05ab27ab","requestUserAgent":"Mozilla/5.0 (Macintosh; Intel Mac OS X 10_15_7) AppleWebKit/537.36 (KHTML, like Gecko) Chrome/142.0.0.0 Safari/537.36","level":"fatal","environment":"production","branch":"main","vercelCache":"","type":"lambda","function":"/api/index.py","host":"tele-git-main-phnxvisioins-projects.vercel.app","deploymentDomain":"tele-git-main-phnxvisioins-projects.vercel.app","deploymentId":"dpl_BJL7eZW3Wc3wsRoo1q3xkX92qsn8","durationMs":-1,"region":"iad1","maxMemoryUsed":-1,"memorySize":-1,"message":"Python process exited with exit status: 1. The logs above can help with debugging the issue.\nPython process exited with exit status: 1. The logs above can help with debugging the issue.","projectId":"prj_Cur5K4TixuWDzJgXyvxVwYeMd2A6","traceId":"","sessionId":"","invocationId":"01K9WZ3XPBXRVP4HC0NRM3VEAX","instanceId":"","concurrency":-1},{"TimeUTC":"2025-11-12 21:21:43","timestampInMs":1762982503601,"requestPath":"tele-fxnfwqv7h-phnxvisioins-projects.vercel.app/favicon.ico","requestMethod":"GET","requestQueryString":"","responseStatusCode":500,"requestId":"sr6cw-1762982503556-247d8e926918","requestUserAgent":"vercel-favicon/1.0","level":"error","environment":"production","branch":"main","vercelCache":"","type":"lambda","function":"/api/index.py","host":"tele-fxnfwqv7h-phnxvisioins-projects.vercel.app","deploymentDomain":"tele-fxnfwqv7h-phnxvisioins-projects.vercel.app","deploymentId":"dpl_BJL7eZW3Wc3wsRoo1q3xkX92qsn8","durationMs":8513,"region":"iad1","maxMemoryUsed":292,"memorySize":2048,"message":"","projectId":"prj_Cur5K4TixuWDzJgXyvxVwYeMd2A6","traceId":"","sessionId":"","invocationId":"01K9WZ495H6A4QGA4RTX3WB2ZW","instanceId":"","concurrency":1},{"TimeUTC":"2025-11-12 21:21:37","timestampInMs":1762982497116,"requestPath":"tele-fxnfwqv7h-phnxvisioins-projects.vercel.app/","requestMethod":"GET","requestQueryString":"","responseStatusCode":-1,"requestId":"fvnlj-1762982488488-17c5b913c977","requestUserAgent":"vercel-favicon/1.0","level":"fatal","environment":"production","branch":"main","vercelCache":"","type":"lambda","function":"/api/index.py","host":"tele-fxnfwqv7h-phnxvisioins-projects.vercel.app","deploymentDomain":"tele-fxnfwqv7h-phnxvisioins-projects.vercel.app","deploymentId":"dpl_BJL7eZW3Wc3wsRoo1q3xkX92qsn8","durationMs":-1,"region":"iad1","maxMemoryUsed":-1,"memorySize":-1,"message":"Python process exited with exit status: 1. The logs above can help with debugging the issue.","projectId":"prj_Cur5K4TixuWDzJgXyvxVwYeMd2A6","traceId":"","sessionId":"","invocationId":"01K9WZ3TJ2P042P7A78V99JPCP","instanceId":"","concurrency":-1},{"TimeUTC":"2025-11-12 21:21:35","timestampInMs":1762982495222,"requestPath":"tele-sandy.vercel.app/favicon.ico","requestMethod":"GET","requestQueryString":"","responseStatusCode":-1,"requestId":"dbs44-1762982486403-99941aa11030","requestUserAgent":"Mozilla/5.0 (Macintosh; Intel Mac OS X 10_15_7) AppleWebKit/537.36 (KHTML, like Gecko) Chrome/142.0.0.0 Safari/537.36","level":"fatal","environment":"production","branch":"main","vercelCache":"","type":"lambda","function":"/api/index.py","host":"tele-sandy.vercel.app","deploymentDomain":"tele-sandy.vercel.app","deploymentId":"dpl_BJL7eZW3Wc3wsRoo1q3xkX92qsn8","durationMs":-1,"region":"iad1","maxMemoryUsed":-1,"memorySize":-1,"message":"Python process exited with exit status: 1. The logs above can help with debugging the issue.","projectId":"prj_Cur5K4TixuWDzJgXyvxVwYeMd2A6","traceId":"","sessionId":"","invocationId":"01K9WZ3RVDY2JNHWGK8Q88E742","instanceId":"","concurrency":-1},{"TimeUTC":"2025-11-12 21:21:34","timestampInMs":1762982494521,"requestPath":"tele-fxnfwqv7h-phnxvisioins-projects.vercel.app/favicon.ico","requestMethod":"GET","requestQueryString":"","responseStatusCode":500,"requestId":"mnlln-1762982494478-d1eeef03c5a0","requestUserAgent":"vercel-favicon/1.0","level":"error","environment":"production","branch":"main","vercelCache":"","type":"lambda","function":"/api/index.py","host":"tele-fxnfwqv7h-phnxvisioins-projects.vercel.app","deploymentDomain":"tele-fxnfwqv7h-phnxvisioins-projects.vercel.app","deploymentId":"dpl_BJL7eZW3Wc3wsRoo1q3xkX92qsn8","durationMs":8602,"region":"iad1","maxMemoryUsed":292,"memorySize":2048,"message":"","projectId":"prj_Cur5K4TixuWDzJgXyvxVwYeMd2A6","traceId":"","sessionId":"","invocationId":"01K9WZ409S053T7TB5D9VY3V41","instanceId":"","concurrency":1},{"TimeUTC":"2025-11-12 21:21:34","timestampInMs":1762982494380,"requestPath":"tele-fxnfwqv7h-phnxvisioins-projects.vercel.app/","requestMethod":"GET","requestQueryString":"","responseStatusCode":500,"requestId":"m42sb-1762982494181-cd8889e49fb0","requestUserAgent":"Mozilla/5.0 (Macintosh; Intel Mac OS X 10_15_7) AppleWebKit/537.36 (KHTML, like Gecko) Chrome/142.0.0.0 Safari/537.36","level":"error","environment":"production","branch":"main","vercelCache":"","type":"lambda","function":"/api/index.py","host":"tele-fxnfwqv7h-phnxvisioins-projects.vercel.app","deploymentDomain":"tele-fxnfwqv7h-phnxvisioins-projects.vercel.app","deploymentId":"dpl_BJL7eZW3Wc3wsRoo1q3xkX92qsn8","durationMs":8238,"region":"iad1","maxMemoryUsed":292,"memorySize":2048,"message":"","projectId":"prj_Cur5K4TixuWDzJgXyvxVwYeMd2A6","traceId":"","sessionId":"","invocationId":"01K9WZ405CTDVP4GFMGJTFZEQD","instanceId":"","concurrency":1},{"TimeUTC":"2025-11-12 21:21:31","timestampInMs":1762982491932,"requestPath":"tele-fxnfwqv7h-phnxvisioins-projects.vercel.app/","requestMethod":"GET","requestQueryString":"","responseStatusCode":500,"requestId":"7g5x8-1762982491892-f2e6fa2a9981","requestUserAgent":"vercel-favicon/1.0","level":"error","environment":"production","branch":"main","vercelCache":"","type":"lambda","function":"/api/index.py","host":"tele-fxnfwqv7h-phnxvisioins-projects.vercel.app","deploymentDomain":"tele-fxnfwqv7h-phnxvisioins-projects.vercel.app","deploymentId":"dpl_BJL7eZW3Wc3wsRoo1q3xkX92qsn8","durationMs":8482,"region":"iad1","maxMemoryUsed":292,"memorySize":2048,"message":"","projectId":"prj_Cur5K4TixuWDzJgXyvxVwYeMd2A6","traceId":"","sessionId":"","invocationId":"01K9WZ3XRWT7CRNXDXY707X0GP","instanceId":"","concurrency":1},{"TimeUTC":"2025-11-12 21:21:31","timestampInMs":1762982491851,"requestPath":"tele-git-main-phnxvisioins-projects.vercel.app/","requestMethod":"GET","requestQueryString":"","responseStatusCode":500,"requestId":"54bv2-1762982491665-4d8c05ab27ab","requestUserAgent":"Mozilla/5.0 (Macintosh; Intel Mac OS X 10_15_7) AppleWebKit/537.36 (KHTML, like Gecko) Chrome/142.0.0.0 Safari/537.36","level":"error","environment":"production","branch":"main","vercelCache":"","type":"lambda","function":"/api/index.py","host":"tele-git-main-phnxvisioins-projects.vercel.app","deploymentDomain":"tele-git-main-phnxvisioins-projects.vercel.app","deploymentId":"dpl_BJL7eZW3Wc3wsRoo1q3xkX92qsn8","durationMs":8367,"region":"iad1","maxMemoryUsed":291,"memorySize":2048,"message":"","projectId":"prj_Cur5K4TixuWDzJgXyvxVwYeMd2A6","traceId":"","sessionId":"","invocationId":"01K9WZ3XPBXRVP4HC0NRM3VEAX","instanceId":"","concurrency":1},{"TimeUTC":"2025-11-12 21:21:28","timestampInMs":1762982488642,"requestPath":"tele-fxnfwqv7h-phnxvisioins-projects.vercel.app/","requestMethod":"GET","requestQueryString":"","responseStatusCode":500,"requestId":"fvnlj-1762982488488-17c5b913c977","requestUserAgent":"vercel-favicon/1.0","level":"error","environment":"production","branch":"main","vercelCache":"","type":"lambda","function":"/api/index.py","host":"tele-fxnfwqv7h-phnxvisioins-projects.vercel.app","deploymentDomain":"tele-fxnfwqv7h-phnxvisioins-projects.vercel.app","deploymentId":"dpl_BJL7eZW3Wc3wsRoo1q3xkX92qsn8","durationMs":8457,"region":"iad1","maxMemoryUsed":292,"memorySize":2048,"message":"","projectId":"prj_Cur5K4TixuWDzJgXyvxVwYeMd2A6","traceId":"","sessionId":"","invocationId":"01K9WZ3TJ2P042P7A78V99JPCP","instanceId":"","concurrency":1},{"TimeUTC":"2025-11-12 21:21:26","timestampInMs":1762982486893,"requestPath":"tele-sandy.vercel.app/favicon.ico","requestMethod":"GET","requestQueryString":"","responseStatusCode":500,"requestId":"dbs44-1762982486403-99941aa11030","requestUserAgent":"Mozilla/5.0 (Macintosh; Intel Mac OS X 10_15_7) AppleWebKit/537.36 (KHTML, like Gecko) Chrome/142.0.0.0 Safari/537.36","level":"error","environment":"production","branch":"main","vercelCache":"","type":"lambda","function":"/api/index.py","host":"tele-sandy.vercel.app","deploymentDomain":"tele-sandy.vercel.app","deploymentId":"dpl_BJL7eZW3Wc3wsRoo1q3xkX92qsn8","durationMs":8307,"region":"iad1","maxMemoryUsed":292,"memorySize":2048,"message":"","projectId":"prj_Cur5K4TixuWDzJgXyvxVwYeMd2A6","traceId":"","sessionId":"","invocationId":"01K9WZ3RVDY2JNHWGK8Q88E742","instanceId":"","concurrency":1},{"TimeUTC":"2025-11-12 21:21:26","timestampInMs":1762982486276,"requestPath":"tele-sandy.vercel.app/","requestMethod":"GET","requestQueryString":"","responseStatusCode":-1,"requestId":"6987f-1762982477160-2cc703d5564d","requestUserAgent":"Mozilla/5.0 (Macintosh; Intel Mac OS X 10_15_7) AppleWebKit/537.36 (KHTML, like Gecko) Chrome/142.0.0.0 Safari/537.36","level":"fatal","environment":"production","branch":"main","vercelCache":"","type":"lambda","function":"/api/index.py","host":"tele-sandy.vercel.app","deploymentDomain":"tele-sandy.vercel.app","deploymentId":"dpl_BJL7eZW3Wc3wsRoo1q3xkX92qsn8","durationMs":-1,"region":"iad1","maxMemoryUsed":-1,"memorySize":-1,"message":"Python process exited with exit status: 1. The logs above can help with debugging the issue.","projectId":"prj_Cur5K4TixuWDzJgXyvxVwYeMd2A6","traceId":"","sessionId":"","invocationId":"01K9WZ3FPF0XN9BRHS2F06BEZ3","instanceId":"","concurrency":-1},{"TimeUTC":"2025-11-12 21:21:17","timestampInMs":1762982477519,"requestPath":"tele-sandy.vercel.app/","requestMethod":"GET","requestQueryString":"","responseStatusCode":500,"requestId":"6987f-1762982477160-2cc703d5564d","requestUserAgent":"Mozilla/5.0 (Macintosh; Intel Mac OS X 10_15_7) AppleWebKit/537.36 (KHTML, like Gecko) Chrome/142.0.0.0 Safari/537.36","level":"error","environment":"production","branch":"main","vercelCache":"","type":"lambda","function":"/api/index.py","host":"tele-sandy.vercel.app","deploymentDomain":"tele-sandy.vercel.app","deploymentId":"dpl_BJL7eZW3Wc3wsRoo1q3xkX92qsn8","durationMs":8738,"region":"iad1","maxMemoryUsed":292,"memorySize":2048,"message":"","projectId":"prj_Cur5K4TixuWDzJgXyvxVwYeMd2A6","traceId":"","sessionId":"","invocationId":"01K9WZ3FPF0XN9BRHS2F06BEZ3","instanceId":"","concurrency":1},{"TimeUTC":"2025-11-12 21:12:20","timestampInMs":1762981940792,"requestPath":"tele-fxnfwqv7h-phnxvisioins-projects.vercel.app/favicon.ico","requestMethod":"GET","requestQueryString":"","responseStatusCode":-1,"requestId":"q6848-1762981932634-581713987755","requestUserAgent":"vercel-screenshot/1.0","level":"fatal","environment":"production","branch":"main","vercelCache":"","type":"lambda","function":"/api/index.py","host":"tele-fxnfwqv7h-phnxvisioins-projects.vercel.app","deploymentDomain":"tele-fxnfwqv7h-phnxvisioins-projects.vercel.app","deploymentId":"dpl_BJL7eZW3Wc3wsRoo1q3xkX92qsn8","durationMs":-1,"region":"iad1","maxMemoryUsed":-1,"memorySize":-1,"message":"Python process exited with exit status: 1. The logs above can help with debugging the issue.","projectId":"prj_Cur5K4TixuWDzJgXyvxVwYeMd2A6","traceId":"","sessionId":"","invocationId":"01K9WYJVM5Q9NQ05BGQM5V4P31","instanceId":"","concurrency":-1},{"TimeUTC":"2025-11-12 21:12:12","timestampInMs":1762981932677,"requestPath":"tele-fxnfwqv7h-phnxvisioins-projects.vercel.app/favicon.ico","requestMethod":"GET","requestQueryString":"","responseStatusCode":500,"requestId":"q6848-1762981932634-581713987755","requestUserAgent":"vercel-screenshot/1.0","level":"error","environment":"production","branch":"main","vercelCache":"","type":"lambda","function":"/api/index.py","host":"tele-fxnfwqv7h-phnxvisioins-projects.vercel.app","deploymentDomain":"tele-fxnfwqv7h-phnxvisioins-projects.vercel.app","deploymentId":"dpl_BJL7eZW3Wc3wsRoo1q3xkX92qsn8","durationMs":8100,"region":"iad1","maxMemoryUsed":292,"memorySize":2048,"message":"","projectId":"prj_Cur5K4TixuWDzJgXyvxVwYeMd2A6","traceId":"","sessionId":"","invocationId":"01K9WYJVM5Q9NQ05BGQM5V4P31","instanceId":"","concurrency":1},{"TimeUTC":"2025-11-12 21:12:12","timestampInMs":1762981932421,"requestPath":"tele-fxnfwqv7h-phnxvisioins-projects.vercel.app/","requestMethod":"GET","requestQueryString":"","responseStatusCode":-1,"requestId":"q6848-1762981924215-c0a842065ee3","requestUserAgent":"vercel-screenshot/1.0","level":"fatal","environment":"production","branch":"main","vercelCache":"","type":"lambda","function":"/api/index.py","host":"tele-fxnfwqv7h-phnxvisioins-projects.vercel.app","deploymentDomain":"tele-fxnfwqv7h-phnxvisioins-projects.vercel.app","deploymentId":"dpl_BJL7eZW3Wc3wsRoo1q3xkX92qsn8","durationMs":-1,"region":"iad1","maxMemoryUsed":-1,"memorySize":-1,"message":"Python process exited with exit status: 1. The logs above can help with debugging the issue.","projectId":"prj_Cur5K4TixuWDzJgXyvxVwYeMd2A6","traceId":"","sessionId":"","invocationId":"01K9WYJKD5APJMCT3B7FZEHDN3","instanceId":"","concurrency":-1},{"TimeUTC":"2025-11-12 21:12:04","timestampInMs":1762981924261,"requestPath":"tele-fxnfwqv7h-phnxvisioins-projects.vercel.app/","requestMethod":"GET","requestQueryString":"","responseStatusCode":500,"requestId":"q6848-1762981924215-c0a842065ee3","requestUserAgent":"vercel-screenshot/1.0","level":"error","environment":"production","branch":"main","vercelCache":"","type":"lambda","function":"/api/index.py","host":"tele-fxnfwqv7h-phnxvisioins-projects.vercel.app","deploymentDomain":"tele-fxnfwqv7h-phnxvisioins-projects.vercel.app","deploymentId":"dpl_BJL7eZW3Wc3wsRoo1q3xkX92qsn8","durationMs":8141,"region":"iad1","maxMemoryUsed":292,"memorySize":2048,"message":"","projectId":"prj_Cur5K4TixuWDzJgXyvxVwYeMd2A6","traceId":"","sessionId":"","invocationId":"01K9WYJKD5APJMCT3B7FZEHDN3","instanceId":"","concurrency":1},{"TimeUTC":"2025-11-12 21:11:59","timestampInMs":1762981919287,"requestPath":"tele-fxnfwqv7h-phnxvisioins-projects.vercel.app/","requestMethod":"GET","requestQueryString":"","responseStatusCode":-1,"requestId":"7g5x8-1762981902317-f8bca25c3dee","requestUserAgent":"vercel-screenshot/1.0","level":"fatal","environment":"production","branch":"main","vercelCache":"","type":"lambda","function":"/api/index.py","host":"tele-fxnfwqv7h-phnxvisioins-projects.vercel.app","deploymentDomain":"tele-fxnfwqv7h-phnxvisioins-projects.vercel.app","deploymentId":"dpl_BJL7eZW3Wc3wsRoo1q3xkX92qsn8","durationMs":-1,"region":"iad1","maxMemoryUsed":-1,"memorySize":-1,"message":"Python process exited with exit status: 1. The logs above can help with debugging the issue.\nPython process exited with exit status: 1. The logs above can help with debugging the issue.","projectId":"prj_Cur5K4TixuWDzJgXyvxVwYeMd2A6","traceId":"","sessionId":"","invocationId":"01K9WYHY4045W408SC97YFHAA7","instanceId":"","concurrency":-1},{"TimeUTC":"2025-11-12 21:11:57","timestampInMs":1762981917826,"requestPath":"tele-fxnfwqv7h-phnxvisioins-projects.vercel.app/","requestMethod":"GET","requestQueryString":"","responseStatusCode":-1,"requestId":"4nzf4-1762981902317-a7ecf41b2235","requestUserAgent":"vercel-screenshot/1.0","level":"fatal","environment":"production","branch":"main","vercelCache":"","type":"lambda","function":"/api/index.py","host":"tele-fxnfwqv7h-phnxvisioins-projects.vercel.app","deploymentDomain":"tele-fxnfwqv7h-phnxvisioins-projects.vercel.app","deploymentId":"dpl_BJL7eZW3Wc3wsRoo1q3xkX92qsn8","durationMs":-1,"region":"iad1","maxMemoryUsed":-1,"memorySize":-1,"message":"Python process exited with exit status: 1. The logs above can help with debugging the issue.\nPython process exited with exit status: 1. The logs above can help with debugging the issue.","projectId":"prj_Cur5K4TixuWDzJgXyvxVwYeMd2A6","traceId":"","sessionId":"","invocationId":"01K9WYHY44W4E1C4FBG0DCE1FZ","instanceId":"","concurrency":-1},{"TimeUTC":"2025-11-12 21:11:56","timestampInMs":1762981916443,"requestPath":"tele-fxnfwqv7h-phnxvisioins-projects.vercel.app/","requestMethod":"GET","requestQueryString":"","responseStatusCode":-1,"requestId":"5f6w5-1762981898203-608fbdb61ced","requestUserAgent":"vercel-screenshot/1.0","level":"fatal","environment":"production","branch":"main","vercelCache":"","type":"lambda","function":"/api/index.py","host":"tele-fxnfwqv7h-phnxvisioins-projects.vercel.app","deploymentDomain":"tele-fxnfwqv7h-phnxvisioins-projects.vercel.app","deploymentId":"dpl_BJL7eZW3Wc3wsRoo1q3xkX92qsn8","durationMs":-1,"region":"iad1","maxMemoryUsed":-1,"memorySize":-1,"message":"Python process exited with exit status: 1. The logs above can help with debugging the issue.\nPython process exited with exit status: 1. The logs above can help with debugging the issue.","projectId":"prj_Cur5K4TixuWDzJgXyvxVwYeMd2A6","traceId":"","sessionId":"","invocationId":"01K9WYHT6Z6AVM52EV7DCJG24N","instanceId":"","concurrency":-1},{"TimeUTC":"2025-11-12 21:11:55","timestampInMs":1762981915738,"requestPath":"tele-fxnfwqv7h-phnxvisioins-projects.vercel.app/","requestMethod":"GET","requestQueryString":"","responseStatusCode":-1,"requestId":"t7qq5-1762981898281-7e7c5a168c76","requestUserAgent":"vercel-screenshot/1.0","level":"fatal","environment":"production","branch":"main","vercelCache":"","type":"lambda","function":"/api/index.py","host":"tele-fxnfwqv7h-phnxvisioins-projects.vercel.app","deploymentDomain":"tele-fxnfwqv7h-phnxvisioins-projects.vercel.app","deploymentId":"dpl_BJL7eZW3Wc3wsRoo1q3xkX92qsn8","durationMs":-1,"region":"iad1","maxMemoryUsed":-1,"memorySize":-1,"message":"Python process exited with exit status: 1. The logs above can help with debugging the issue.\nPython process exited with exit status: 1. The logs above can help with debugging the issue.","projectId":"prj_Cur5K4TixuWDzJgXyvxVwYeMd2A6","traceId":"","sessionId":"","invocationId":"01K9WYHT6WC432FD9R5PW3Z07W","instanceId":"","concurrency":-1},{"TimeUTC":"2025-11-12 21:11:42","timestampInMs":1762981902468,"requestPath":"tele-fxnfwqv7h-phnxvisioins-projects.vercel.app/","requestMethod":"GET","requestQueryString":"","responseStatusCode":500,"requestId":"4nzf4-1762981902317-a7ecf41b2235","requestUserAgent":"vercel-screenshot/1.0","level":"error","environment":"production","branch":"main","vercelCache":"","type":"lambda","function":"/api/index.py","host":"tele-fxnfwqv7h-phnxvisioins-projects.vercel.app","deploymentDomain":"tele-fxnfwqv7h-phnxvisioins-projects.vercel.app","deploymentId":"dpl_BJL7eZW3Wc3wsRoo1q3xkX92qsn8","durationMs":7417,"region":"iad1","maxMemoryUsed":292,"memorySize":2048,"message":"","projectId":"prj_Cur5K4TixuWDzJgXyvxVwYeMd2A6","traceId":"","sessionId":"","invocationId":"01K9WYHY44W4E1C4FBG0DCE1FZ","instanceId":"","concurrency":1},{"TimeUTC":"2025-11-12 21:11:42","timestampInMs":1762981902463,"requestPath":"tele-fxnfwqv7h-phnxvisioins-projects.vercel.app/","requestMethod":"GET","requestQueryString":"","responseStatusCode":500,"requestId":"7g5x8-1762981902317-f8bca25c3dee","requestUserAgent":"vercel-screenshot/1.0","level":"error","environment":"production","branch":"main","vercelCache":"","type":"lambda","function":"/api/index.py","host":"tele-fxnfwqv7h-phnxvisioins-projects.vercel.app","deploymentDomain":"tele-fxnfwqv7h-phnxvisioins-projects.vercel.app","deploymentId":"dpl_BJL7eZW3Wc3wsRoo1q3xkX92qsn8","durationMs":8157,"region":"iad1","maxMemoryUsed":291,"memorySize":2048,"message":"","projectId":"prj_Cur5K4TixuWDzJgXyvxVwYeMd2A6","traceId":"","sessionId":"","invocationId":"01K9WYHY4045W408SC97YFHAA7","instanceId":"","concurrency":1},{"TimeUTC":"2025-11-12 21:11:38","timestampInMs":1762981898463,"requestPath":"tele-fxnfwqv7h-phnxvisioins-projects.vercel.app/","requestMethod":"GET","requestQueryString":"","responseStatusCode":500,"requestId":"5f6w5-1762981898203-608fbdb61ced","requestUserAgent":"vercel-screenshot/1.0","level":"error","environment":"production","branch":"main","vercelCache":"","type":"lambda","function":"/api/index.py","host":"tele-fxnfwqv7h-phnxvisioins-projects.vercel.app","deploymentDomain":"tele-fxnfwqv7h-phnxvisioins-projects.vercel.app","deploymentId":"dpl_BJL7eZW3Wc3wsRoo1q3xkX92qsn8","durationMs":8565,"region":"iad1","maxMemoryUsed":292,"memorySize":2048,"message":"","projectId":"prj_Cur5K4TixuWDzJgXyvxVwYeMd2A6","traceId":"","sessionId":"","invocationId":"01K9WYHT6Z6AVM52EV7DCJG24N","instanceId":"","concurrency":1},{"TimeUTC":"2025-11-12 21:11:38","timestampInMs":1762981898460,"requestPath":"tele-fxnfwqv7h-phnxvisioins-projects.vercel.app/","requestMethod":"GET","requestQueryString":"","responseStatusCode":500,"requestId":"t7qq5-1762981898281-7e7c5a168c76","requestUserAgent":"vercel-screenshot/1.0","level":"error","environment":"production","branch":"main","vercelCache":"","type":"lambda","function":"/api/index.py","host":"tele-fxnfwqv7h-phnxvisioins-projects.vercel.app","deploymentDomain":"tele-fxnfwqv7h-phnxvisioins-projects.vercel.app","deploymentId":"dpl_BJL7eZW3Wc3wsRoo1q3xkX92qsn8","durationMs":8358,"region":"iad1","maxMemoryUsed":292,"memorySize":2048,"message":"","projectId":"prj_Cur5K4TixuWDzJgXyvxVwYeMd2A6","traceId":"","sessionId":"","invocationId":"01K9WYHT6WC432FD9R5PW3Z07W","instanceId":"","concurrency":1}]